Metadata-Version: 1.1
Name: pywehaclientlib
Version: 1.0.1
Summary: WEHA Client Library
Home-page: https://github.com/wahhid/weha_client_library
Author: Wahyu Hidayat
Author-email: wahhid@gmail.com
License: MIT
Download-URL: https://github.com/wahhid/weha_client_library
Keywords: library api flask appbuilder odoo couchdb
Platform: UNKNOWN
Classifier: Development Status :: 3 - Alpha
Classifier: Intended Audience :: Developers
Classifier: Topic :: Software Development :: Build Tools
Classifier: License :: OSI Approved :: MIT License
Classifier: Programming Language :: Python :: 2
Classifier: Programming Language :: Python :: 2.6
Classifier: Programming Language :: Python :: 2.7
Classifier: Programming Language :: Python :: 3.5
Classifier: Programming Language :: Python :: 3.6
Classifier: Programming Language :: Python :: 3.7
Classifier: Programming Language :: Python :: 3.8
Classifier: Programming Language :: Python :: 3.9
